VexHubUtils/__init__.py
VexHubUtils-0.1.1.dist-info/METADATA
VexHubUtils-0.1.1.dist-info/WHEEL
VexHubUtils-0.1.1.dist-info/top_level.txt
VexHubUtils-0.1.1.dist-info/RECORD
