Metadata-Version: 2.1
Name: VexHubUtils
Version: 0.1.1
Summary: A package for Vex Hub utilities
Author: COMPLEX
Author-email: complex@vexhub.dev
